odoo/addons/product_uom_use_type/README.rst
odoo/addons/product_uom_use_type/__init__.py
odoo/addons/product_uom_use_type/__manifest__.py
odoo/addons/product_uom_use_type/demo/product_template.xml
odoo/addons/product_uom_use_type/demo/product_uom.xml
odoo/addons/product_uom_use_type/demo/res_groups.xml
odoo/addons/product_uom_use_type/i18n/ca.po
odoo/addons/product_uom_use_type/i18n/es.po
odoo/addons/product_uom_use_type/i18n/fr.po
odoo/addons/product_uom_use_type/i18n/it.po
odoo/addons/product_uom_use_type/i18n/product_uom_use_type.pot
odoo/addons/product_uom_use_type/models/__init__.py
odoo/addons/product_uom_use_type/models/product_product.py
odoo/addons/product_uom_use_type/models/product_template.py
odoo/addons/product_uom_use_type/models/product_uom.py
odoo/addons/product_uom_use_type/readme/CONFIGURE.rst
odoo/addons/product_uom_use_type/readme/CONTRIBUTORS.rst
odoo/addons/product_uom_use_type/readme/DESCRIPTION.rst
odoo/addons/product_uom_use_type/static/description/icon.png
odoo/addons/product_uom_use_type/static/description/index.html
odoo/addons/product_uom_use_type/static/description/use_type_form.png
odoo/addons/product_uom_use_type/static/description/use_type_list.png
odoo/addons/product_uom_use_type/static/src/img/demo/bier_faucheuse.png
odoo/addons/product_uom_use_type/tests/__init__.py
odoo/addons/product_uom_use_type/tests/test_module.py
odoo/addons/product_uom_use_type/views/view_product_uom.xml
odoo_addon_product_uom_use_type-16.0.1.0.0.6.dist-info/METADATA
odoo_addon_product_uom_use_type-16.0.1.0.0.6.dist-info/WHEEL
odoo_addon_product_uom_use_type-16.0.1.0.0.6.dist-info/top_level.txt
odoo_addon_product_uom_use_type-16.0.1.0.0.6.dist-info/RECORD
